spydr/__init__.py
spydr/utils.py
spydr/webdriver.py
spydr-0.6.1.dist-info/LICENSE
spydr-0.6.1.dist-info/METADATA
spydr-0.6.1.dist-info/WHEEL
spydr-0.6.1.dist-info/top_level.txt
spydr-0.6.1.dist-info/RECORD
