Metadata-Version: 2.1
Name: spydr
Version: 0.6.1
Summary: Selenium Python WebDriver Wrapper - Commonly used WebDriver functionality in a package
Home-page: https://github.com/aaronchen/spydr
Author: Aaron Chen
Author-email: aaron@611b.com
License: MIT
Keywords: spydr,selenium,python,webdriver,wrapper
Platform: any
Classifier: Programming Language :: Python :: 3.8
Classifier: License :: OSI Approved :: MIT License
Classifier: Operating System :: OS Independent
Requires-Python: >=3.8
Requires-Dist: PyYAML (>=5.3.1)
Requires-Dist: python-dateutil (>=2.8.1)
Requires-Dist: selenium (>=3.141.0)
Requires-Dist: webdriver-manager (>=3.2.2)
